pysdrlib/__init__.py
pysdrlib/devices.py
pysdrlib/err.py
pysdrlib/logger.py
pysdrlib/warn.py
pysdrlib/UHD/README.md
pysdrlib/UHD/__init__.py
pysdrlib/UHD/b210.py
pysdrlib/UHD/config.py
pysdrlib/_ext/__init__.py
pysdrlib/_ext/hackrf.py
pysdrlib/_ext/utils.py
pysdrlib/base/__init__.py
pysdrlib/base/buffer.py
pysdrlib/base/config.py
pysdrlib/base/device.py
pysdrlib/base/formats.py
pysdrlib/base/io.py
pysdrlib/bladerf/README.md
pysdrlib/bladerf/__init__.py
pysdrlib/bladerf/bladerf.py
pysdrlib/bladerf/config.py
pysdrlib/extio/README.md
pysdrlib/extio/__init__.py
pysdrlib/extio/config.py
pysdrlib/extio/rx888.py
pysdrlib/file/__init__.py
pysdrlib/file/err.py
pysdrlib/file/file.py
pysdrlib/hackrf/README.md
pysdrlib/hackrf/__init__.py
pysdrlib/hackrf/config.py
pysdrlib/hackrf/hackrf.py
pysdrlib/hackrf/bin/__init__.py
pysdrlib/hackrf/bin/hackrf_info.py
pysdrlib/hackrf/bin/hackrf_transfer.py
pysdrlib/hackrf/data/build/CMakeCache.txt
pysdrlib/hackrf/data/build/CMakeFiles/CMakeConfigureLog.yaml
pysdrlib/hackrf/data/build/CMakeFiles/cmake.check_cache
pysdrlib/hackrf/data/build/CMakeFiles/4.2.1/CMakeCCompiler.cmake
pysdrlib/hackrf/data/build/CMakeFiles/4.2.1/CMakeDetermineCompilerABI_C.bin
pysdrlib/hackrf/data/build/CMakeFiles/4.2.1/CMakeSystem.cmake
pysdrlib/hackrf/data/build/CMakeFiles/4.2.1/CompilerIdC/CMakeCCompilerId.c
pysdrlib/hackrf/data/build/CMakeFiles/4.2.1/CompilerIdC/a.out
pysdrlib/hackrf/data/cmake/cmake_uninstall.cmake.in
pysdrlib/hackrf/data/cmake/set_release.cmake
pysdrlib/hackrf/data/cmake/modules/FindFFTW3f.cmake
pysdrlib/hackrf/data/cmake/modules/FindLIBUSB.cmake
pysdrlib/hackrf/data/libhackrf/53-hackrf.rules
pysdrlib/hackrf/data/libhackrf/53-hackrf.rules.in
pysdrlib/hackrf/data/libhackrf/CMakeLists.txt
pysdrlib/hackrf/data/libhackrf/HackRFConfig.cmake
pysdrlib/hackrf/data/libhackrf/libhackrf.pc.in
pysdrlib/hackrf/data/libhackrf/src/CMakeLists.txt
pysdrlib/hackrf/data/libhackrf/src/hackrf.c
pysdrlib-0.1.3.dist-info/METADATA
pysdrlib-0.1.3.dist-info/WHEEL
pysdrlib-0.1.3.dist-info/top_level.txt
pysdrlib-0.1.3.dist-info/RECORD
pysdrlib-0.1.3.dist-info/licenses/LICENSE
