Metadata-Version: 2.1
Name: pysdrlib
Version: 0.1.3
Summary: wrapper for hardware SDRs
Author-email: Anonoei <to+dev@an0.us>
Project-URL: Homepage, https://github.com/Anonoei/pysdrlib
Project-URL: Documentation, https://anonoei.github.io/pysdrlib/
Project-URL: Repository, https://github.com/Anonoei/pysdrlib.git
Project-URL: Issues, https://github.com/Anonoei/pysdrlib/issues
Project-URL: Source, https://github.com/anonoei/pysdrlib
Keywords: anonoei,sdr
Classifier: Development Status :: 4 - Beta
Classifier: Intended Audience :: Developers
Classifier: Natural Language :: English
Classifier: Topic :: Scientific/Engineering
Classifier: Topic :: Communications
Classifier: Programming Language :: Python :: 3
Classifier: Programming Language :: Python :: 3 :: Only
Classifier: Programming Language :: Cython
Classifier: Programming Language :: C
Classifier: Operating System :: OS Independent
Requires-Python: >=3.8
License-File: LICENSE
Requires-Dist: numpy
Provides-Extra: dev
Requires-Dist: twine ; extra == 'dev'
Requires-Dist: build ; extra == 'dev'
Requires-Dist: bumpver ; extra == 'dev'
Requires-Dist: pytest ; extra == 'dev'
Requires-Dist: pdoc3 ; extra == 'dev'
